morsey.py
morsey-0.1.3.dist-info/METADATA
morsey-0.1.3.dist-info/WHEEL
morsey-0.1.3.dist-info/licenses/LICENSE
morsey-0.1.3.dist-info/RECORD
