Metadata-Version: 2.1
Name: morsey
Version: 0.1.3
Summary: Contains methods to translate morse code and english str objects.
Project-URL: Homepage, https://github.com/AHarnishPM/morsey
Project-URL: Bug Tracker, https://github.com/AHarnishPM/morsey/issues
Author-email: Aaron Harnish <aaronjharnish@gmail.com>
License-File: LICENSE
Classifier: License :: OSI Approved :: MIT License
Classifier: Operating System :: OS Independent
Classifier: Programming Language :: Python :: 3.9
Requires-Python: >=3.9
